setup.py
src/MotionDetect/MotionDetect.py
src/MotionDetect/__init__.py
src/MotionDetect.egg-info/PKG-INFO
src/MotionDetect.egg-info/SOURCES.txt
src/MotionDetect.egg-info/dependency_links.txt
src/MotionDetect.egg-info/requires.txt
src/MotionDetect.egg-info/top_level.txt