Metadata-Version: 1.2
Name: MotionDetect
Version: 0.0.9
Summary: library 
Home-page: http://10.177.132.101
Author: Lujx
Author-email: 20920139@qq.com
License: MIT Licence
Keywords: MotionDetect
Platform: any
Requires-Python: >=3.6.*
